rocinante/__init__.py
rocinante/application.py
rocinante/blueprint.py
rocinante/cache.py
rocinante/cors.py
rocinante/endpoint.py
rocinante/handler.py
rocinante/middleware.py
rocinante/request.py
rocinante/response.py
rocinante/route.py
rocinante/status.py
rocinante/websocket.py
rocinante/wrapper.py
Rocinante-2.0.dist-info/LICENSE
Rocinante-2.0.dist-info/METADATA
Rocinante-2.0.dist-info/WHEEL
Rocinante-2.0.dist-info/top_level.txt
Rocinante-2.0.dist-info/RECORD
